appsniffer/__init__.py
appsniffer/main.py
appsniffer-2.0.0.dist-info/LICENSE
appsniffer-2.0.0.dist-info/METADATA
appsniffer-2.0.0.dist-info/WHEEL
appsniffer-2.0.0.dist-info/entry_points.txt
appsniffer-2.0.0.dist-info/top_level.txt
appsniffer-2.0.0.dist-info/RECORD
