Metadata-Version: 2.1
Name: appsniffer
Version: 2.0.0
Summary: Интерактивный скрипт для поиска информации о приложениях в Google Play Market.
Home-page: https://t.me/+VFiT6gd42ehhNzYy
Author: Avinion
Author-email: shizofrin@gmail.com
Classifier: Programming Language :: Python :: 3
Classifier: License :: OSI Approved :: MIT License
Classifier: Operating System :: OS Independent
Requires-Python: >=3.6
License-File: LICENSE
Requires-Dist: google-play-scraper
